reposaurus/__init__.py
reposaurus/cli/__init__.py
reposaurus/cli/main.py
reposaurus/cli/commands/__init__.py
reposaurus/cli/commands/base.py
reposaurus/cli/commands/detect_idiots.py
reposaurus/cli/commands/fetch.py
reposaurus/cli/commands/init_config.py
reposaurus/cli/commands/init_ignore.py
reposaurus/config/__init__.py
reposaurus/config/ignore_template.py
reposaurus/config/manager.py
reposaurus/config/patterns/__init__.py
reposaurus/core/__init__.py
reposaurus/core/analysis.py
reposaurus/core/exclusions.py
reposaurus/core/output.py
reposaurus/core/processor.py
reposaurus/core/secrets.py
reposaurus/utils/__init__.py
reposaurus/utils/filesystem.py
reposaurus/utils/formatting.py
reposaurus/utils/versioning.py
tests/__init__.py
tests/conftest.py
tests/debug_secrets.py
tests/test_helpers.py
tests/integration/__init__.py
tests/integration/cli/__init__.py
tests/integration/cli/test_cli_commands.py
tests/integration/cli/test_cli_outputs.py
tests/unit/__init__.py
reposaurus-1.0.0.dist-info/METADATA
reposaurus-1.0.0.dist-info/WHEEL
reposaurus-1.0.0.dist-info/entry_points.txt
reposaurus-1.0.0.dist-info/top_level.txt
reposaurus-1.0.0.dist-info/RECORD
